odoo8_addon_purchase_all_shipments-8.0.1.0.0.99.dev11-py3.8-nspkg.pth
odoo_addons/purchase_all_shipments/README.rst
odoo_addons/purchase_all_shipments/__init__.py
odoo_addons/purchase_all_shipments/__openerp__.py
odoo_addons/purchase_all_shipments/i18n/de.po
odoo_addons/purchase_all_shipments/i18n/es.po
odoo_addons/purchase_all_shipments/i18n/fi.po
odoo_addons/purchase_all_shipments/i18n/fr.po
odoo_addons/purchase_all_shipments/i18n/fr_FR.po
odoo_addons/purchase_all_shipments/i18n/it.po
odoo_addons/purchase_all_shipments/i18n/nl.po
odoo_addons/purchase_all_shipments/i18n/pt_BR.po
odoo_addons/purchase_all_shipments/i18n/purchase_all_shipments.pot
odoo_addons/purchase_all_shipments/i18n/ro.po
odoo_addons/purchase_all_shipments/i18n/sl.po
odoo_addons/purchase_all_shipments/model/__init__.py
odoo_addons/purchase_all_shipments/model/purchase_order.py
odoo_addons/purchase_all_shipments/static/description/icon.png
odoo_addons/purchase_all_shipments/tests/__init__.py
odoo_addons/purchase_all_shipments/tests/test_three_step_reception.py
odoo_addons/purchase_all_shipments/view/purchase_order.xml
odoo8_addon_purchase_all_shipments-8.0.1.0.0.99.dev11.dist-info/METADATA
odoo8_addon_purchase_all_shipments-8.0.1.0.0.99.dev11.dist-info/WHEEL
odoo8_addon_purchase_all_shipments-8.0.1.0.0.99.dev11.dist-info/namespace_packages.txt
odoo8_addon_purchase_all_shipments-8.0.1.0.0.99.dev11.dist-info/top_level.txt
odoo8_addon_purchase_all_shipments-8.0.1.0.0.99.dev11.dist-info/RECORD
